{
    "configurations": [
        {
            "name": "Mac",
            "includePath": [
                "${workspaceFolder}/**",
                "/usr/local/include",
                "/usr/local/opt/qt5/include",
                "/usr/local/Cellar/qt@5/5.15.2/include",
                "/opt/homebrew/include",
                "/opt/homebrew/Cellar/qt@5/5.15.2/include"
            ],
            "defines": [],
            "macFrameworkPath": [
                "/Library/Developer/CommandLineTools/SDKs/MacOSX15.sdk/System/Library/Frameworks"
            ],
            "cStandard": "c17",
            "cppStandard": "c++17",
            "intelliSenseMode": "macos-clang-arm64"
        }
    ],
    "version": 4
}